grepath.py
grepath-1.1.1.data/scripts/grepath
grepath-1.1.1.dist-info/DESCRIPTION.rst
grepath-1.1.1.dist-info/METADATA
grepath-1.1.1.dist-info/RECORD
grepath-1.1.1.dist-info/WHEEL
grepath-1.1.1.dist-info/metadata.json
grepath-1.1.1.dist-info/top_level.txt
